{
  "gitSyncId": "67303ef6bcf71f4b5bed5b9d_04378c33-160d-47d0-b891-dd8ce9999076",
  "id": "Equipamentos_CreateEquipment",
  "pluginId": "postgres-plugin",
  "pluginType": "DB",
  "unpublishedAction": {
    "actionConfiguration": {
      "body": "BEGIN;\nINSERT INTO public.equipment (title, description, custom, image_url) values \n(\n    {{this.params.title}},\n    {{this.params.description}},\n    {{this.params.custom}},\n    {{this.params.image_url}}\n);\nCOMMIT;",
      "encodeParamsToggle": true,
      "paginationType": "NONE",
      "pluginSpecifiedTemplates": [
        {
          "value": true
        }
      ],
      "timeoutInMillisecond": 10000
    },
    "confirmBeforeExecute": false,
    "datasource": {
      "id": "workoutapp @ supabase",
      "isAutoGenerated": false,
      "name": "workoutapp @ supabase",
      "pluginId": "postgres-plugin"
    },
    "dynamicBindingPathList": [
      {
        "key": "body"
      }
    ],
    "executeOnLoad": false,
    "name": "CreateEquipment",
    "pageId": "Equipamentos",
    "userSetOnLoad": false
  }
}